dina_test/__init__.py
dina_test/dinaTest.py
dina_test-0.1.2.dist-info/WHEEL
dina_test-0.1.2.dist-info/METADATA
dina_test-0.1.2.dist-info/RECORD
